uhsr/__init__.py
uhsr/bm25.py
uhsr/core.py
uhsr/faiss_retrieval.py
uhsr/reranker.py
uhsr/similarity.py
uhsr/utils.py
uhsr/vector_db.py
uhsr-0.2.8.dist-info/LICENSE
uhsr-0.2.8.dist-info/METADATA
uhsr-0.2.8.dist-info/WHEEL
uhsr-0.2.8.dist-info/top_level.txt
uhsr-0.2.8.dist-info/RECORD
