Metadata-Version: 2.2
Name: uhsr
Version: 0.2.8
Summary: Unified Hyperbolic Spectral Retrieval (UHSR) - a novel text retrieval algorithm combining lexical and semantic search.
Home-page: https://github.com/vedaant00/uhsr
Author: Vedaant Singh
Keywords: uhsr,text retrieval,BM25,FAISS,Pinecone,vector search,semantic search,lexical search,spectral re-ranking,machine learning,NLP
Classifier: Programming Language :: Python :: 3.6
Classifier: Programming Language :: Python :: 3.7
Classifier: Programming Language :: Python :: 3.8
Classifier: Programming Language :: Python :: 3.9
Classifier: Programming Language :: Python :: 3.10
Classifier: License :: OSI Approved :: MIT License
Classifier: Operating System :: OS Independent
Classifier: Topic :: Scientific/Engineering :: Artificial Intelligence
Requires-Python: >=3.6
License-File: LICENSE
Requires-Dist: numpy
Requires-Dist: sentence-transformers
Requires-Dist: pinecone-client
Requires-Dist: openai
Provides-Extra: gpu
Requires-Dist: faiss-gpu; extra == "gpu"
Provides-Extra: cpu
Requires-Dist: faiss-cpu; extra == "cpu"
Dynamic: author
Dynamic: classifier
Dynamic: description
Dynamic: description-content-type
Dynamic: home-page
Dynamic: keywords
Dynamic: provides-extra
Dynamic: requires-dist
Dynamic: requires-python
Dynamic: summary
